wemux-0.1.0.dist-info/METADATA
wemux-0.1.0.dist-info/WHEEL
wemux-0.1.0.dist-info/entry_points.txt
wemux-0.1.0.dist-info/licenses/LICENSE
wemux/__init__.py
wemux/dispatcher.py
wemux/errors.py
wemux/handler.py
wemux/iterator.py
wemux/message.py
wemux/messagebus.py
wemux-0.1.0.dist-info/RECORD
